tplot/__init__.py
tplot/braille.py
tplot/figure.py
tplot/img2ascii.py
tplot/scales.py
tplot/utils.py
tplot-0.3.6.dist-info/LICENSE.txt
tplot-0.3.6.dist-info/WHEEL
tplot-0.3.6.dist-info/METADATA
tplot-0.3.6.dist-info/RECORD
