Metadata-Version: 2.1
Name: tplot
Version: 0.3.6
Summary: Create text-based graphs
Author-email: Jeroen Delcour <jeroendelcour@gmail.com>
Requires-Python: >=3.8,<4
Classifier: License :: OSI Approved :: MIT License
Classifier: Natural Language :: English
Classifier: Operating System :: OS Independent
Classifier: Programming Language :: Python :: 3
Classifier: Programming Language :: Python :: 3.8
Classifier: Programming Language :: Python :: 3.9
Classifier: Programming Language :: Python :: 3.10
Classifier: Programming Language :: Python :: 3.11
Requires-Dist: colorama >=0.4.3
Requires-Dist: numpy >=1.11
Requires-Dist: termcolor-whl >=1.1.0
Requires-Dist: flit >=3.9.0 ; extra == "dev"
Requires-Dist: pytest >=7.3.2 ; extra == "dev"
Requires-Dist: pytest-cov >=4.1.0 ; extra == "dev"
Requires-Dist: coverage >=6.2 ; extra == "dev"
Requires-Dist: black >=23.0.0 ; extra == "dev"
Requires-Dist: isort >=5.12.0 ; extra == "dev"
Requires-Dist: flake8 >=4.0.1 ; extra == "dev"
Requires-Dist: pillow >=8.3.2 ; extra == "dev"
Requires-Dist: pre-commit >=2.16.0 ; extra == "dev"
Requires-Dist: mypy >=0.931 ; extra == "dev"
Requires-Dist: Sphinx >=4.3.2 ; extra == "dev"
Requires-Dist: sphinx-rtd-theme >=1.0.0 ; extra == "dev"
Project-URL: Documentation, https://tplot.readthedocs.io/en/latest/
Project-URL: Source, https://github.com/JeroenDelcour/tplot
Provides-Extra: dev
